CONTRIBUTORS.txt
MANIFEST.in
README.txt
setup.cfg
setup.py
docs/HISTORY.txt
docs/INSTALL.txt
docs/LICENSE.GPL
docs/LICENSE.txt
mailtoplone/__init__.py
mailtoplone.scrawl.egg-info/PKG-INFO
mailtoplone.scrawl.egg-info/SOURCES.txt
mailtoplone.scrawl.egg-info/dependency_links.txt
mailtoplone.scrawl.egg-info/entry_points.txt
mailtoplone.scrawl.egg-info/namespace_packages.txt
mailtoplone.scrawl.egg-info/not-zip-safe
mailtoplone.scrawl.egg-info/paster_plugins.txt
mailtoplone.scrawl.egg-info/requires.txt
mailtoplone.scrawl.egg-info/top_level.txt
mailtoplone/scrawl/CHANGELOG
mailtoplone/scrawl/README.txt
mailtoplone/scrawl/__init__.py
mailtoplone/scrawl/adapter.py
mailtoplone/scrawl/blogentryfactory.py
mailtoplone/scrawl/config.py
mailtoplone/scrawl/configure.zcml
mailtoplone/scrawl/interfaces.py
mailtoplone/scrawl/utilities.py
mailtoplone/scrawl/tests/__init__.py
mailtoplone/scrawl/tests/base.py
mailtoplone/scrawl/tests/test_doctest.py