Metadata-Version: 1.0
Name: mailtoplone.scrawl
Version: 0.1
Summary: addon for mailtoplone creating Scrawl Blog Entries
Home-page: http://svn.plone.org/svn/collective/mailtoplone/mailtoplone.scrawl/tags/0.1
Author: Hans-Peter Locher
Author-email: hans-peter.locher@inquant.de
License: GPL
Platform: UNKNOWN
Classifier: Framework :: Plone
Classifier: Intended Audience :: Developers
Classifier: Topic :: Software Development :: Libraries :: Python Modules
Classifier: License :: OSI Approved :: GNU General Public License (GPL)
